montague_testapps/__init__.py
montague_testapps/apps.py
montague_testapps/configapps.py
montague_testapps/servers.py
montague_testapps-0.1.3.dist-info/DESCRIPTION.rst
montague_testapps-0.1.3.dist-info/entry_points.txt
montague_testapps-0.1.3.dist-info/METADATA
montague_testapps-0.1.3.dist-info/metadata.json
montague_testapps-0.1.3.dist-info/RECORD
montague_testapps-0.1.3.dist-info/top_level.txt
montague_testapps-0.1.3.dist-info/WHEEL
